MANIFEST.in
README.rst
setup.cfg
setup.py
versioneer.py
ASAPTools.egg-info/PKG-INFO
ASAPTools.egg-info/SOURCES.txt
ASAPTools.egg-info/dependency_links.txt
ASAPTools.egg-info/requires.txt
ASAPTools.egg-info/top_level.txt
asaptools/__init__.py
asaptools/_version.py
asaptools/partition.py
asaptools/simplecomm.py
asaptools/timekeeper.py
asaptools/version.py
asaptools/vprinter.py